Metadata-Version: 1.0
Name: satori-remote
Version: 0.1.0
Summary: Package for Remote acquisition of Satori Images
Home-page: UNKNOWN
Author: Satori-NG org
Author-email: satori_ng@email.com
License: UNKNOWN
Platform: UNKNOWN
